qade/__init__.py
qade/bases.py
qade/equations.py
qade/functions.py
qade/regression.py
qade-0.1.2.dist-info/LICENSE.txt
qade-0.1.2.dist-info/METADATA
qade-0.1.2.dist-info/WHEEL
qade-0.1.2.dist-info/top_level.txt
qade-0.1.2.dist-info/RECORD
