Metadata-Version: 2.1
Name: qade
Version: 0.1.2
Summary: Differential equation solving through quantum annealing
Author: Juan Carlos Criado, Michael Spannowsky
License: Copyright (c) <year> <copyright holders>        
Keywords: differential equations,quantum annealing
Platform: UNKNOWN
Classifier: Programming Language :: Python :: 3
Requires-Python: >=3.7
License-File: LICENSE.txt
Requires-Dist: dwave-ocean-sdk
Requires-Dist: numpy (>=1.20)
